natswork_client/__init__.py
natswork_client/async_support.py
natswork_client/cli.py
natswork_client/client.py
natswork_client/config.py
natswork_client/dispatcher.py
natswork_client/exceptions.py
natswork_client/job.py
natswork_client/messages.py
natswork_client/nats_client.py
natswork_client/result_handler.py
natswork_client/status_tracker.py
natswork_client-0.0.1.dist-info/METADATA
natswork_client-0.0.1.dist-info/WHEEL
natswork_client-0.0.1.dist-info/licenses/LICENSE
natswork_client-0.0.1.dist-info/RECORD
