Metadata-Version: 2.4
Name: natswork-client
Version: 0.0.1
Summary: Client library for NatsWork job processing system
Project-URL: Homepage, https://github.com/tesote/nats-work
Project-URL: Repository, https://github.com/tesote/nats-work
Project-URL: Documentation, https://github.com/tesote/nats-work/tree/main/docs/python
Project-URL: Bug Reports, https://github.com/tesote/nats-work/issues
Project-URL: Changelog, https://github.com/tesote/nats-work/blob/main/CHANGELOG.md
Author-email: NatsWork Contributors <natswork@tesote.com>
License: MIT
License-File: LICENSE
Keywords: distributed,jobs,nats,queue,worker
Classifier: Development Status :: 3 - Alpha
Classifier: Intended Audience :: Developers
Classifier: License :: OSI Approved :: MIT License
Classifier: Operating System :: OS Independent
Classifier: Programming Language :: Python :: 3
Classifier: Programming Language :: Python :: 3.8
Classifier: Programming Language :: Python :: 3.9
Classifier: Programming Language :: Python :: 3.10
Classifier: Programming Language :: Python :: 3.11
Classifier: Programming Language :: Python :: 3.12
Classifier: Topic :: Software Development :: Libraries :: Python Modules
Classifier: Topic :: System :: Distributed Computing
Requires-Python: >=3.8
Requires-Dist: nats-py<3.0.0,>=2.4.0
Requires-Dist: pydantic<3.0.0,>=2.0.0
Requires-Dist: typing-extensions>=4.0.0
Provides-Extra: dev
Requires-Dist: black>=23.0.0; extra == 'dev'
Requires-Dist: mypy>=1.5.0; extra == 'dev'
Requires-Dist: pre-commit>=3.0.0; extra == 'dev'
Requires-Dist: pytest-asyncio>=0.21.0; extra == 'dev'
Requires-Dist: pytest-cov>=4.0.0; extra == 'dev'
Requires-Dist: pytest>=7.0.0; extra == 'dev'
Requires-Dist: ruff>=0.1.0; extra == 'dev'
Provides-Extra: test
Requires-Dist: pytest-asyncio>=0.21.0; extra == 'test'
Requires-Dist: pytest-cov>=4.0.0; extra == 'test'
Requires-Dist: pytest>=7.0.0; extra == 'test'
Requires-Dist: testcontainers>=3.7.0; extra == 'test'
